AUTHORS
INSTALL
LICENSE
MANIFEST.in
README
setup.py
DjangoSEO.egg-info/PKG-INFO
DjangoSEO.egg-info/SOURCES.txt
DjangoSEO.egg-info/dependency_links.txt
DjangoSEO.egg-info/namespace_packages.txt
DjangoSEO.egg-info/requires.txt
DjangoSEO.egg-info/top_level.txt
docs/Makefile
docs/conf.py
docs/contents.txt
docs/index.txt
docs/introduction/blitz-tutorial.txt
docs/introduction/index.txt
docs/introduction/installation.txt
docs/introduction/overview.txt
docs/introduction/tutorial.txt
docs/reference/administrators.txt
docs/reference/definition.txt
docs/reference/development.txt
docs/reference/index.txt
docs/reference/images/admin-index.png
docs/reference/images/admin-model.png
docs/reference/images/admin-modelinstance-inline.png
docs/reference/images/admin-path.png
docs/reference/images/admin-sites-i18n.png
docs/reference/images/admin-view.png
docs/topics/best-practices.txt
docs/topics/index.txt
regressiontests/README
regressiontests/__init__.py
regressiontests/manage.py
regressiontests/settings.py
regressiontests/test-coverage.py
regressiontests/urls.py
regressiontests/userapp/__init__.py
regressiontests/userapp/admin.py
regressiontests/userapp/models.py
regressiontests/userapp/seo.py
regressiontests/userapp/tests.py
regressiontests/userapp/urls.py
regressiontests/userapp/views.py
regressiontests/userapp/templates/my_view.html
regressiontests/userapp/templates/object_detail.html
rollyourown/__init__.py
rollyourown/seo/__init__.py
rollyourown/seo/admin.py
rollyourown/seo/backends.py
rollyourown/seo/base.py
rollyourown/seo/default.py
rollyourown/seo/fields.py
rollyourown/seo/models.py
rollyourown/seo/options.py
rollyourown/seo/systemviews.py
rollyourown/seo/utils.py
rollyourown/seo/management/__init__.py
rollyourown/seo/management/commands/__init__.py
rollyourown/seo/management/commands/populate_metadata.py
rollyourown/seo/templatetags/__init__.py
rollyourown/seo/templatetags/seo.py