Metadata-Version: 1.0
Name: DjangoSEO
Version: 1.0
Summary: A framework for managing SEO metadata in Django.
Home-page: https://github.com/willhardy/django-seo
Author: Will Hardy
Author-email: djangoseo@willhardy.com.au
License: LICENSE
Keywords: seo,django,framework
Platform: UNKNOWN
Classifier: Development Status :: 4 - Beta
Classifier: Environment :: Web Environment
Classifier: Framework :: Django
Classifier: Intended Audience :: Developers
Classifier: Programming Language :: Python
Classifier: License :: OSI Approved :: Apache Software License
Classifier: License :: OSI Approved :: BSD License
Classifier: Operating System :: OS Independent
Classifier: Topic :: Software Development
